{
	"comment": "Spirit Island box has 283mm x 283mm (x65mm?) of internal space",
	"item-types": {
		"cards-in-mayday-standard-sleeve": {
			"width": 88.2,
			"height": 63.7,
			"thickness": 0.50,
			"needs_indent": true,
			"comment": "412 cards total in game"
		},
		"cards-in-mayday-mini-euro-sleeve": {
			"width": 68.2,
			"height": 44.2,
			"thickness": 0.50,
			"needs_indent": true,
			"comment": "23 cards total in game"
		},
		"invaders-7-wide": {
			"width": 60,
			"height": 24,
			"thickness": 10,
			"forbid_indent": true
		},
		"player-markers": {
			"width": 45,
			"height": 24,
			"thickness": 28,
			"forbid_indent": true
		},
		"badlands-tokens": {
			"width": 45,
			"height": 24,
			"thickness": 1.6,
			"forbid_indent": true
		}
	},
	"trays": [
		{
			"name": "power-cards",
			"description": "power cards, needed during play",
			"dimensions": {
				"width": 94.5,
				"height": 92
			},
			"columns": [
				{
					"elastic": true,
					"slots": [
						{
							"item": "cards-in-mayday-standard-sleeve",
							"amount": 100,
							"label": "Minor Powers",
							"elastic": true
						},
						{
							"item": "cards-in-mayday-standard-sleeve",
							"amount": 66,
							"label": "Major Powers",
							"elastic": true
						}
					]
				}
			]
		},
		{
			"name": "events",
			"description": "events, needed during play",
			"dimensions": {
				"width": 94.5,
				"height": 37
			},
			"columns": [
				{
					"elastic": true,
					"slots": [
						{
							"item": "cards-in-mayday-standard-sleeve",
							"amount": 62,
							"label": "Event cards",
							"elastic": true
						}
					]
				}
			]
		},
		{
			"name":"big-cards-2",
			"description": "spirit cards and everything else needed in setup",
			"dimensions": {
				"width": 94.5,
				"height": 141
			},
			"columns":
			[
				{
					"elastic": true,
					"slots": [
						{
							"item": "cards-in-mayday-standard-sleeve",
							"amount": 167,
							"label": "Spirit Powers",
							"elastic": true
						},
						{
							"item": "cards-in-mayday-standard-sleeve",
							"amount": 23,
							"label": "Blight cards",
							"elastic": true
						},
						{
							"item": "cards-in-mayday-standard-sleeve",
							"amount": 50,
							"label": "Fear cards",
							"elastic": true
						}
					]
				}
			]
		},
		{
			"name": "player-markers",
			"description": "Colored player markers",
			"dimensions": {
				"width": 52,
				"height": 185.5
			},
			"columns": [
				{
					"elastic": true,
					"slots": [
						{
							"item": "player-markers",
							"amount": 1,
							"label": "Blue",
							"elastic": true
						},
						{
							"item": "player-markers",
							"amount": 1,
							"label": "Red",
							"elastic": true
						},
						{
							"item": "player-markers",
							"amount": 1,
							"label": "Yellow",
							"elastic": true
						},
						{
							"item": "player-markers",
							"amount": 1,
							"label": "Green",
							"elastic": true
						},
						{
							"item": "player-markers",
							"amount": 1,
							"label": "Orange",
							"elastic": true
						},
						{
							"item": "player-markers",
							"amount": 1,
							"label": "Pink",
							"elastic": true
						}
					]
				}
			]
		},
		{
			"name": "beast-tokens",
			"description": "Special effect tokens such as Beasts, Diseases, etc",
			"dimensions": {
				"width": 52,
				"height": 185.5
			},
			"columns": [
				{
					"elastic": true,
					"slots": [
						{
							"item": "badlands-tokens",
							"amount": 35,
							"label": "Beasts",
							"elastic": true
						},
						{
							"item": "badlands-tokens",
							"amount": 22,
							"label": "Strife",
							"elastic": true
						},
						{
							"item": "badlands-tokens",
							"amount": 22,
							"label": "Wilds",
							"elastic": true
						},
						{
							"item": "badlands-tokens",
							"amount": 30,
							"label": "Disease",
							"elastic": true
						}
					]
				}
			]
		},
		{
			"name": "invaders",
			"description": "Invader-sized pieces",
			"dimensions": {
				"width": 70.5,
				"height": 200
			},
			"columns": [
				{
					"elastic": true,
					"slots": [
						{
							"item": "invaders-7-wide",
							"amount": 7,
							"label": "Explorers",
							"elastic": true
						},
						{
							"item": "invaders-7-wide",
							"amount": 7,
							"label": "Towns",
							"elastic": true
						},
						{
							"item": "invaders-7-wide",
							"amount": 5,
							"label": "Cities",
							"elastic": true
						}
					]
				}
			]
		},
		{
			"name": "board-pieces",
			"description": "Dahans, blight etc",
			"dimensions": {
				"width": 70.5,
				"height": 200
			},
			"columns": [
				{
					"elastic": true,
					"slots": [
						{
							"item": "invaders-7-wide",
							"amount": 7,
							"label": "Explorers",
							"elastic": true
						},
						{
							"item": "invaders-7-wide",
							"amount": 7,
							"label": "Towns",
							"elastic": true
						},
						{
							"item": "invaders-7-wide",
							"amount": 5,
							"label": "Cities",
							"elastic": true
						}
					]
				}
			]
		}

	]
}

